{
  "preferences": {
    "readonly": true,
    "autosave": true
  },
  "session": {
    "open files": [
      "C:\\Users\\robert\\Documents\\test.txt",
      "C:\\Users\\robert\\Documents\\test4.txt"
    ],
    "recent files": [
      {
        "file": "C:\\Users\\robert\\Documents\\test2.txt",
        "atime": 1776107038.470923
      },
      {
        "file": "C:\\Users\\robert\\Documents\\test.csv",
        "atime": 1776107048.786505
      },
      {
        "file": "C:\\Users\\robert\\Documents\\test4.txt",
        "atime": 1776117466.604074
      },
      {
        "file": "C:\\Users\\robert\\Documents\\test.txt",
        "atime": 1776117466.598956
      }
    ],
    "closed files": [
      {
        "file": "C:\\Users\\robert\\Documents\\VS Code Files\\InharNumbers\\InharNumbers.py",
        "atime": 1776117302.921937
      },
      {
        "file": "C:\\Users\\robert\\Documents\\test.html",
        "atime": 1776117302.922021
      },
      {
        "file": "C:\\Users\\robert\\Documents\\test3.txt",
        "atime": 1776117302.922269
      },
      {
        "file": "C:\\Users\\robert\\Documents\\test.json",
        "atime": 1776117502.497034
      },
      {
        "file": "C:\\Users\\robert\\Documents\\VS Code Files\\TextEditor\\TODO.md",
        "atime": 1776117509.140449
      }
    ]
  }
}